gssdata/__init__.py
gssdata/core.py
gssdata/data.py
gssdata-0.1.1.dist-info/METADATA
gssdata-0.1.1.dist-info/WHEEL
gssdata-0.1.1.dist-info/licenses/LICENSE
gssdata-0.1.1.dist-info/RECORD
