Metadata-Version: 2.4
Name: gssdata
Version: 0.1.1
Summary: Python client for General Social Survey (GSS) data
Project-URL: Homepage, https://github.com/MaxGhenis/gss
Project-URL: Documentation, https://maxghenis.github.io/gss
Project-URL: Repository, https://github.com/MaxGhenis/gss
Project-URL: Issues, https://github.com/MaxGhenis/gss/issues
Author-email: Max Ghenis <max@policyengine.org>
License-Expression: MIT
License-File: LICENSE
Keywords: general social survey,gss,norc,social science,survey data
Classifier: Development Status :: 4 - Beta
Classifier: Intended Audience :: Science/Research
Classifier: License :: OSI Approved :: MIT License
Classifier: Programming Language :: Python :: 3
Classifier: Programming Language :: Python :: 3.9
Classifier: Programming Language :: Python :: 3.10
Classifier: Programming Language :: Python :: 3.11
Classifier: Programming Language :: Python :: 3.12
Classifier: Topic :: Scientific/Engineering
Requires-Python: >=3.9
Requires-Dist: pandas>=1.5.0
Requires-Dist: requests>=2.28.0
Provides-Extra: dev
Requires-Dist: pytest-cov>=4.0.0; extra == 'dev'
Requires-Dist: pytest>=7.0.0; extra == 'dev'
Requires-Dist: ruff>=0.1.0; extra == 'dev'
Provides-Extra: docs
Requires-Dist: mkdocs-material>=9.0.0; extra == 'docs'
Requires-Dist: mkdocs>=1.5.0; extra == 'docs'
Requires-Dist: mkdocstrings[python]>=0.24.0; extra == 'docs'
